<?xml version="1.0" encoding="UTF-8"?>
<!DOCTYPE pkgmetadata SYSTEM "http://www.gentoo.org/dtd/metadata.dtd">
<pkgmetadata>
	<maintainer>
		<email>idl0r@gentoo.org</email>
		<name>Christian Ruppert</name>
	</maintainer>
	<maintainer>
		<email>wfischer@thomas-krenn.com</email>
		<name>Werner Fischer</name>
		<description>Upstream Maintainer (please CC on bugs)</description>
	</maintainer>
	<maintainer>
		<email>dev-zero@gentoo.org</email>
		<name>Tiziano Müller</name>
	</maintainer>
	<maintainer>
		<email>chutzpah@gentoo.org</email>
		<name>Patrick McLean</name>
	</maintainer>
	<maintainer>
		<email>robbat2@gentoo.org</email>
		<name>Robin H. Johnson</name>
	</maintainer>
	<maintainer>
		<email>tampakrap@gentoo.org</email>
		<name>Theo Chatzimichos</name>
	</maintainer>
	<maintainer>
		<email>proxy-maint@gentoo.org</email>
		<name>Proxy Maintainers</name>
	</maintainer>
	</pkgmetadata>
